surinort_ast/__init__.py
surinort_ast/exceptions.py
surinort_ast/version.py
surinort_ast/analysis/__init__.py
surinort_ast/analysis/conflicts_outline.py
surinort_ast/analysis/coverage.py
surinort_ast/analysis/estimator.py
surinort_ast/analysis/lsh.py
surinort_ast/analysis/minhash.py
surinort_ast/analysis/optimizer.py
surinort_ast/analysis/strategies.py
surinort_ast/api/__init__.py
surinort_ast/api/_internal.py
surinort_ast/api/parsing.py
surinort_ast/api/printing.py
surinort_ast/api/serialization.py
surinort_ast/api/validation.py
surinort_ast/builder/__init__.py
surinort_ast/builder/option_builders.py
surinort_ast/builder/rule_builder.py
surinort_ast/cli/__init__.py
surinort_ast/cli/main.py
surinort_ast/cli/shared.py
surinort_ast/cli/commands/__init__.py
surinort_ast/cli/commands/format.py
surinort_ast/cli/commands/from_json.py
surinort_ast/cli/commands/parse.py
surinort_ast/cli/commands/plugins.py
surinort_ast/cli/commands/schema.py
surinort_ast/cli/commands/stats.py
surinort_ast/cli/commands/to_json.py
surinort_ast/cli/commands/validate.py
surinort_ast/core/__init__.py
surinort_ast/core/diagnostics.py
surinort_ast/core/enums.py
surinort_ast/core/location.py
surinort_ast/core/nodes.py
surinort_ast/core/visitor.py
surinort_ast/parsing/__init__.py
surinort_ast/parsing/factory.py
surinort_ast/parsing/grammar.lark
surinort_ast/parsing/helpers.py
surinort_ast/parsing/interfaces.py
surinort_ast/parsing/lark_parser.py
surinort_ast/parsing/parser.py
surinort_ast/parsing/parser_config.py
surinort_ast/parsing/transformer.py
surinort_ast/parsing/mixins/__init__.py
surinort_ast/parsing/mixins/address_transformer.py
surinort_ast/parsing/mixins/content_transformer.py
surinort_ast/parsing/mixins/header_transformer.py
surinort_ast/parsing/mixins/option_transformer.py
surinort_ast/parsing/mixins/port_transformer.py
surinort_ast/parsing/mixins/options/__init__.py
surinort_ast/parsing/mixins/options/_helpers.py
surinort_ast/parsing/mixins/options/buffer_mixin.py
surinort_ast-1.1.0.dist-info/METADATA
surinort_ast-1.1.0.dist-info/WHEEL
surinort_ast-1.1.0.dist-info/entry_points.txt
surinort_ast-1.1.0.dist-info/licenses/LICENSE
surinort_ast-1.1.0.dist-info/RECORD
