Metadata-Version: 2.4
Name: surinort-ast
Version: 1.1.0
Summary: Production-grade Abstract Syntax Tree parser for IDS rules (Suricata/Snort) with comprehensive validation and serialization support
Project-URL: Homepage, https://github.com/seifreed/surinort-ast
Project-URL: Documentation, https://seifreed.github.io/surinort-ast
Project-URL: Repository, https://github.com/seifreed/surinort-ast
Project-URL: Issues, https://github.com/seifreed/surinort-ast/issues
Project-URL: Changelog, https://github.com/seifreed/surinort-ast/blob/main/CHANGELOG.md
Project-URL: Source, https://github.com/seifreed/surinort-ast
Project-URL: Bug Tracker, https://github.com/seifreed/surinort-ast/issues
Project-URL: Release Notes, https://github.com/seifreed/surinort-ast/releases
Project-URL: Discussions, https://github.com/seifreed/surinort-ast/discussions
Author-email: Marc Rivero López <mriverolopez@gmail.com>
Maintainer-email: Marc Rivero López <mriverolopez@gmail.com>
License: GPL-3.0-or-later
License-File: LICENSE
Keywords: ast,cybersecurity,ids,intrusion-detection,ips,malware-analysis,network-monitoring,network-security,parser,pcap,rule-parser,security,signature-analysis,snort,suricata,threat-detection
Classifier: Development Status :: 5 - Production/Stable
Classifier: Intended Audience :: Developers
Classifier: Intended Audience :: Information Technology
Classifier: Intended Audience :: Science/Research
Classifier: Intended Audience :: System Administrators
Classifier: License :: OSI Approved :: GNU General Public License v3 or later (GPLv3+)
Classifier: Natural Language :: English
Classifier: Operating System :: MacOS :: MacOS X
Classifier: Operating System :: Microsoft :: Windows
Classifier: Operating System :: OS Independent
Classifier: Operating System :: POSIX :: Linux
Classifier: Programming Language :: Python :: 3
Classifier: Programming Language :: Python :: 3.11
Classifier: Programming Language :: Python :: 3.12
Classifier: Programming Language :: Python :: 3.13
Classifier: Programming Language :: Python :: 3.14
Classifier: Programming Language :: Python :: Implementation :: CPython
Classifier: Topic :: Security
Classifier: Topic :: Software Development :: Compilers
Classifier: Topic :: Software Development :: Interpreters
Classifier: Topic :: Software Development :: Libraries :: Python Modules
Classifier: Topic :: System :: Networking :: Monitoring
Classifier: Typing :: Typed
Requires-Python: >=3.11
Requires-Dist: jsonschema>=4.25.1
Requires-Dist: lark>=1.3.1
Requires-Dist: pydantic>=2.12.5
Requires-Dist: typer>=0.21.0
Provides-Extra: all
Requires-Dist: bandit>=1.9.2; extra == 'all'
Requires-Dist: build>=1.3.0; extra == 'all'
Requires-Dist: hypothesis>=6.148.8; extra == 'all'
Requires-Dist: mkdocs-material>=9.7.1; extra == 'all'
Requires-Dist: msgpack>=1.1.2; extra == 'all'
Requires-Dist: mypy>=1.19.1; extra == 'all'
Requires-Dist: networkx>=3.6.1; extra == 'all'
Requires-Dist: pre-commit>=4.5.1; extra == 'all'
Requires-Dist: protobuf>=6.33.2; extra == 'all'
Requires-Dist: pytest-benchmark>=5.2.3; extra == 'all'
Requires-Dist: pytest-cov>=7.0.0; extra == 'all'
Requires-Dist: pytest>=9.0.2; extra == 'all'
Requires-Dist: python-magic>=0.4.27; extra == 'all'
Requires-Dist: pyyaml>=6.0.3; extra == 'all'
Requires-Dist: rich>=14.2.0; extra == 'all'
Requires-Dist: ruff>=0.14.10; extra == 'all'
Requires-Dist: safety>=3.7.0; extra == 'all'
Requires-Dist: twine>=6.2.0; extra == 'all'
Provides-Extra: analysis
Requires-Dist: networkx>=3.6.1; extra == 'analysis'
Provides-Extra: benchmark
Requires-Dist: pytest-benchmark>=5.2.3; extra == 'benchmark'
Provides-Extra: cli-enhanced
Requires-Dist: rich>=14.2.0; extra == 'cli-enhanced'
Provides-Extra: dev
Requires-Dist: build>=1.3.0; extra == 'dev'
Requires-Dist: hypothesis>=6.148.8; extra == 'dev'
Requires-Dist: mkdocs-material>=9.7.1; extra == 'dev'
Requires-Dist: mypy>=1.19.1; extra == 'dev'
Requires-Dist: pre-commit>=4.5.1; extra == 'dev'
Requires-Dist: pytest-cov>=7.0.0; extra == 'dev'
Requires-Dist: pytest>=9.0.2; extra == 'dev'
Requires-Dist: ruff>=0.14.10; extra == 'dev'
Requires-Dist: twine>=6.2.0; extra == 'dev'
Provides-Extra: formats
Requires-Dist: python-magic>=0.4.27; extra == 'formats'
Requires-Dist: pyyaml>=6.0.3; extra == 'formats'
Provides-Extra: security
Requires-Dist: bandit>=1.9.2; extra == 'security'
Requires-Dist: safety>=3.7.0; extra == 'security'
Provides-Extra: serialization
Requires-Dist: msgpack>=1.1.2; extra == 'serialization'
Requires-Dist: protobuf>=6.33.2; extra == 'serialization'
